newsreader-0.3.0.data/data/man/man1/nr.1
newsreader-0.3.0.data/data/man/man5/nr-config.5
nr/__init__.py
nr/article.py
nr/main.py
nr/site.py
newsreader-0.3.0.dist-info/LICENSE
newsreader-0.3.0.dist-info/METADATA
newsreader-0.3.0.dist-info/WHEEL
newsreader-0.3.0.dist-info/entry_points.txt
newsreader-0.3.0.dist-info/pbr.json
newsreader-0.3.0.dist-info/top_level.txt
newsreader-0.3.0.dist-info/RECORD
